CaozuoxitongJiaochengCYuyanBianchengWang/README.md
CaozuoxitongJiaochengCYuyanBianchengWang/__init__.py
CaozuoxitongJiaochengCYuyanBianchengWang/__main__.py
CaozuoxitongJiaochengCYuyanBianchengWang/file.epub
CaozuoxitongJiaochengCYuyanBianchengWang/index.html
CaozuoxitongJiaochengCYuyanBianchengWang/css/__init__.py
CaozuoxitongJiaochengCYuyanBianchengWang/css/annotations.css
CaozuoxitongJiaochengCYuyanBianchengWang/css/main.css
CaozuoxitongJiaochengCYuyanBianchengWang/css/normalize.css
CaozuoxitongJiaochengCYuyanBianchengWang/css/popup.css
CaozuoxitongJiaochengCYuyanBianchengWang/font/__init__.py
CaozuoxitongJiaochengCYuyanBianchengWang/font/fontello.eot
CaozuoxitongJiaochengCYuyanBianchengWang/font/fontello.svg
CaozuoxitongJiaochengCYuyanBianchengWang/font/fontello.ttf
CaozuoxitongJiaochengCYuyanBianchengWang/font/fontello.woff
CaozuoxitongJiaochengCYuyanBianchengWang/img/__init__.py
CaozuoxitongJiaochengCYuyanBianchengWang/img/annotator-glyph-sprite.png
CaozuoxitongJiaochengCYuyanBianchengWang/img/annotator-icon-sprite.png
CaozuoxitongJiaochengCYuyanBianchengWang/img/apple-touch-icon.png
CaozuoxitongJiaochengCYuyanBianchengWang/img/cancelfullscreen.png
CaozuoxitongJiaochengCYuyanBianchengWang/img/close.png
CaozuoxitongJiaochengCYuyanBianchengWang/img/fullscreen.png
CaozuoxitongJiaochengCYuyanBianchengWang/img/loader.gif
CaozuoxitongJiaochengCYuyanBianchengWang/img/menu-icon.png
CaozuoxitongJiaochengCYuyanBianchengWang/img/save.png
CaozuoxitongJiaochengCYuyanBianchengWang/img/saved.png
CaozuoxitongJiaochengCYuyanBianchengWang/img/settings-s.png
CaozuoxitongJiaochengCYuyanBianchengWang/img/settings.png
CaozuoxitongJiaochengCYuyanBianchengWang/img/star.png
CaozuoxitongJiaochengCYuyanBianchengWang/js/__init__.py
CaozuoxitongJiaochengCYuyanBianchengWang/js/epub.js
CaozuoxitongJiaochengCYuyanBianchengWang/js/epub.min.js
CaozuoxitongJiaochengCYuyanBianchengWang/js/epub.min.map
CaozuoxitongJiaochengCYuyanBianchengWang/js/hooks.min.js
caozuoxitong_jiaocheng_c_yuyan_biancheng_wang-2024.3.2.0.dist-info/METADATA
caozuoxitong_jiaocheng_c_yuyan_biancheng_wang-2024.3.2.0.dist-info/WHEEL
caozuoxitong_jiaocheng_c_yuyan_biancheng_wang-2024.3.2.0.dist-info/entry_points.txt
caozuoxitong_jiaocheng_c_yuyan_biancheng_wang-2024.3.2.0.dist-info/top_level.txt
caozuoxitong_jiaocheng_c_yuyan_biancheng_wang-2024.3.2.0.dist-info/RECORD
